ChangeLog
LICENSE
MANIFEST.in
README.md
README.rst
setup.py
testit.py
doc/func_timeout.StoppableThread.html
doc/func_timeout.dafunc.html
doc/func_timeout.exceptions.html
doc/func_timeout.html
doc/func_timeout.py2_raise.html
doc/func_timeout.py3_raise.html
doc/index.html
func_timeout/StoppableThread.py
func_timeout/__init__.py
func_timeout/dafunc.py
func_timeout/exceptions.py
func_timeout/py2_raise.py
func_timeout/py3_raise.py
func_timeout.egg-info/PKG-INFO
func_timeout.egg-info/SOURCES.txt
func_timeout.egg-info/dependency_links.txt
func_timeout.egg-info/top_level.txt
tests/README
tests/runTests.py
tests/FuncTimeoutTests/TestUtils.py
tests/FuncTimeoutTests/test_Basic.py
tests/FuncTimeoutTests/test_Decorator.py
tests/FuncTimeoutTests/test_TestUtils.py
tests/FuncTimeoutTests/test_TestUtilsSleep.py
tests/FuncTimeoutTests/test_TestUtilsSleepWithArgs.py