Metadata-Version: 1.1
Name: func-timeout
Version: 4.1.0
Summary: Python module which allows you to specify timeouts when calling any existing function
Home-page: https://github.com/kata198/func_timeout
Author: Tim Savannah
Author-email: kata198@gmail.com
License: LGPLv2
Keywords: function,timeout,call,terminate,runtime,max,seconds,after,execution
Platform: UNKNOWN
Classifier: Development Status :: 5 - Production/Stable
Classifier: Programming Language :: Python
Classifier: License :: OSI Approved :: GNU Lesser General Public License v2 (LGPLv2)
Classifier: Programming Language :: Python :: 2
Classifier: Programming Language :: Python :: 2.7
Classifier: Programming Language :: Python :: 3.4
Classifier: Programming Language :: Python :: 3.5
Classifier: Topic :: Software Development :: Libraries :: Python Modules
